{
  "group": "mushroomquest",
  "type": "minecraft:crafting_shapeless",
  "ingredients": [
    {
      "item": "mushroomquest:octopusstinkhorn"
    },
    {
      "item": "mushroomquest:deadmansfingers"
    },
    {
      "item": "mushroomquest:devilsbolete"
    },
    {
      "item": "minecraft:fermented_spider_eye"
    },
    {
      "item": "mushroomquest:mortarandpestle"
    },
    {
      "item": "minecraft:gunpowder"
    }
  ],
  "result": {
    "item": "mushroomquest:devilsbrew",
    "count": 1
  }
}