{
  "pools": [
    {
      "name": "library",
      "rolls": {
        "min": 10,
        "max": 16
      },
      "entries": [
        {
          "type": "minecraft:item",
          "name": "apotheosis:scrap_tome",
          "weight": 3
        },
        {
          "type": "minecraft:item",
          "name": "quark:ancient_tome",
          "weight": 1,
          "functions": [
            {
              "function": "minecraft:set_nbt",
              "tag": "{StoredEnchantments:[{lvl:5,id:\"uniquee:sages_blessing\"}]}"
            }
          ]
        },
        {
          "type": "minecraft:item",
          "name": "enigmaticlegacy:lore_inscriber",
          "weight": 1
        },
        {
          "type": "minecraft:item",
          "name": "enigmaticlegacy:lore_fragment",
          "weight": 2,
          "functions": [
            {
              "function": "set_count",
              "count": {
                "min": 1,
                "max": 2
              }
            }
          ]
        },
        {
          "type": "minecraft:item",
          "name": "buddycards:pack.1",
          "weight": 2,
          "functions": [
            {
              "function": "set_count",
              "count": {
                "min": 1,
                "max": 3
              }
            }
          ]
        },
        {
          "type": "minecraft:item",
          "name": "titles:title_fragment",
          "weight": 2,
          "functions": [
            {
              "function": "set_count",
              "count": {
                "min": 1,
                "max": 3
              }
            }
          ]
        },
        {
          "type": "minecraft:item",
          "name": "waystones:warp_scroll",
          "weight": 2
        },
        {
          "type": "minecraft:item",
          "name": "minecraft:book",
          "weight": 9,
          "functions": [
            {
              "function": "set_count",
              "count": {
                "min": 2,
                "max": 4
              }
            }
          ]
        },
        {
          "type": "minecraft:item",
          "name": "minecraft:ink_sac",
          "weight": 3,
          "functions": [
            {
              "function": "set_count",
              "count": {
                "min": 1,
                "max": 3
              }
            }
          ]
        },
        {
          "type": "minecraft:item",
          "name": "minecraft:feather",
          "weight": 6,
          "functions": [
            {
              "function": "set_count",
              "count": {
                "min": 2,
                "max": 4
              }
            }
          ]
        },
        {
          "type": "minecraft:item",
          "name": "minecraft:writable_book",
          "weight": 6,
          "functions": [
            {
              "function": "set_count",
              "count": {
                "min": 1,
                "max": 2
              }
            }
          ]
        },
        {
          "type": "minecraft:item",
          "name": "minecraft:cobweb",
          "weight": 18,
          "functions": [
            {
              "function": "set_count",
              "count": {
                "min": 4,
                "max": 10
              }
            }
          ]
        },
        {
          "type": "minecraft:item",
          "name": "minecraft:book",
          "weight": 9,
          "functions": [
            {
              "function": "dungeoncrawl:enchanted_book",
              "loot_level": 3
            }
          ]
        }
      ]
    }
  ]
}