{
  "biomes": [
    [
      {
        "type": "BIOME_DICT",
        "negate": false,
        "value": "overworld"
      },
      {
        "type": "BIOME_DICT",
        "negate": false,
        "value": "snowy"
      },
      {
        "type": "BIOME_DICT",
        "negate": false,
        "value": "wasteland"
      }
    ],
    [
      {
        "type": "BIOME_DICT",
        "negate": false,
        "value": "overworld"
      },
      {
        "type": "BIOME_DICT",
        "negate": false,
        "value": "snowy"
      },
      {
        "type": "BIOME_DICT",
        "negate": false,
        "value": "forest"
      }
    ],
    [
      {
        "type": "REGISTRY_NAME",
        "negate": false,
        "value": "biomesoplenty:snowy_coniferous_forest"
      }
    ],
    [
      {
        "type": "REGISTRY_NAME",
        "negate": false,
        "value": "biomesoplenty:snowy_fir_clearing"
      }
    ],
    [
      {
        "type": "REGISTRY_NAME",
        "negate": false,
        "value": "snowy_maple_woods"
      }
    ],
    [
      {
        "type": "REGISTRY_NAME",
        "negate": false,
        "value": "terralith:alpine_grove"
      }
    ],
    [
      {
        "type": "REGISTRY_NAME",
        "negate": false,
        "value": "terralith:snowy_badlands"
      }
    ],
    [
      {
        "type": "REGISTRY_NAME",
        "negate": false,
        "value": "terralith:snowy_maple_forest"
      }
    ],
    [
      {
        "type": "REGISTRY_NAME",
        "negate": false,
        "value": "terralith:snowy_shield"
      }
    ],
    [
      {
        "type": "REGISTRY_NAME",
        "negate": false,
        "value": "terralith:wintry_forest"
      }
    ],
    [
      {
        "type": "REGISTRY_NAME",
        "negate": false,
        "value": "terralith:wintry_lowlands"
      }
    ],
    [
      {
        "type": "REGISTRY_NAME",
        "negate": false,
        "value": "terralith:gravel_desert"
      }
    ],
    [
      {
        "type": "REGISTRY_NAME",
        "negate": false,
        "value": "terralith:skylands_winter"
      }
    ]
  ]
}